{
    "schemaVersion": 1,
    "id": "${mod_id}",
    "version": "${version}",
    "name": "${mod_name}",
    "description": "${description}",
    "authors": [
        "${mod_author}"
    ],
    "contact": {
        "homepage": "https://twitter.com/TeamAbodeMC",
        "sources": "https://github.com/Team-Abode/verdance"
    },
    "license": "${license}",
    "icon": "${mod_id}.png",
    "environment": "*",
    "entrypoints": {
        "main": [
            "com.teamabode.verdance.VerdanceFabric"
        ]
    },
    "mixins": [
        "${mod_id}.mixins.json",
        "${mod_id}.fabric.mixins.json"
    ],
    "accessWidener": "verdance.accesswidener",
    "depends": {
        "fabricloader": ">=${fabric_loader_version}",
        "fabric-api": "*",
        "minecraft": "${minecraft_version}",
        "java": ">=${java_version}"
    },
    "suggests": {}
}
  